Metadata-Version: 2.1
Name: regularizecl
Version: 2022.3.16
Summary: angular power spectra regularization
Home-page: https://github.com/cltools/regularizecl
Maintainer: Nicolas Tessore
Maintainer-email: n.tessore@ucl.ac.uk
License: MIT
Project-URL: Documentation, https://cltools.readthedocs.io/regularizecl/
Project-URL: Issues, https://github.com/cltools/regularizecl/issues
Platform: UNKNOWN
Classifier: Programming Language :: Python :: 3
Classifier: License :: OSI Approved :: MIT License
Classifier: Operating System :: OS Independent
Requires-Python: >=3.6
